{
	"inspections": [{
		"1": {
			"recordDamage": {
				"id": 1,
				"location": "Woonkamer",
				"newDamage": "Ja",
				"type": "Calamiteit",
				"date": "2023-01-16T19:20+01:00",
				"immediateAction": "Ja",
				"description": "Gat in de deur"
			},
			"recordOverdueMaintenance": {
				"id": 2,
				"location": "Zolder",
				"type": "Houtrot",
				"immediateAction": "Ja",
				"Kostenindicatie": "1500+"
			},
			"inspectTechnicalInstallations": {
				"id": 3,
				"location": "Keuken",
				"type": "verwarming",
				"reportedMalfunction": "Ja",
				"test": "test1.pdf",
				"approved": "Ja",
				"description": "Kleine gele plek op het plafond als gevolg van lekkage"
			},
			"identifyModifications": {
				"id": 4,
				"existing": "existing1.pdf",
				"place": "Keuken",
				"executed": "huurder",
				"description": "Nieuwe tegels",
				"action": "accepteren",
				"decription": "nieuwe witte tegels geplaatst, geen bezwaar"
			}

		},
		"1": {
			"recordDamage": {
				"id": 5,
				"location": "Woonkamer",
				"newDamage": "Ja",
				"type": "Calamiteit",
				"date": "2023-01-28T14:16+01:00",
				"immediateAction": "Ja",
				"description": "Gat in de deur"
			},
			"recordOverdueMaintenance": {
				"id": 6,
				"location": "Zolder",
				"type": "Houtrot",
				"immediateAction": "Ja",
				"Kostenindicatie": "1500+"
			},
			"inspectTechnicalInstallations": {
				"id": 7,
				"location": "Keuken",
				"type": "verwarming",
				"reportedMalfunction": "Ja",
				"test": "test2.pdf",
				"approved": "Ja",
				"description": "Kleine gele plek op het plafond als gevolg van lekkage"
			},
			"identifyModifications": {
				"id": 8,
				"existing": "existing2.pdf",
				"place": "Keuken",
				"executed": "huurder",
				"description": "Nieuwe tegels",
				"action": "accepteren",
				"decription": "nieuwe witte tegels geplaatst, geen bezwaar"
			}

		}
	}
]}
